swb_meter/__init__.py
swb_meter/__main__.py
swb_meter/cli.py
swb_meter/db.py
swb_meter/logger.py
swb_meter/parser.py
swb_meter/streamlit.py
swb_meter-0.1.0.dist-info/LICENSE
swb_meter-0.1.0.dist-info/METADATA
swb_meter-0.1.0.dist-info/WHEEL
swb_meter-0.1.0.dist-info/entry_points.txt
swb_meter-0.1.0.dist-info/top_level.txt
swb_meter-0.1.0.dist-info/RECORD
