Metadata-Version: 2.1
Name: swb-meter
Version: 0.1.0
Summary: switch-bot meters server
Author: kj-9
License: Apache-2.0
Project-URL: Homepage, https://github.com/kj-9/swb-meter
Project-URL: Changelog, https://github.com/kj-9/swb-meter/releases
Project-URL: Issues, https://github.com/kj-9/swb-meter/issues
Project-URL: CI, https://github.com/kj-9/swb-meter/actions
Classifier: License :: OSI Approved :: Apache Software License
Requires-Python: >=3.8
License-File: LICENSE
Requires-Dist: click
Requires-Dist: bleak
Requires-Dist: sqlite-utils
Provides-Extra: streamlit
Requires-Dist: streamlit ; extra == 'streamlit'
Requires-Dist: plotly ; extra == 'streamlit'
Provides-Extra: test
Requires-Dist: pytest ; extra == 'test'
Requires-Dist: pre-commit ; extra == 'test'
Requires-Dist: cogapp ; extra == 'test'
